{
	"ProgFileFolder":	"",
	"ProjTemplateFolder":	"",
	"ProjSaveFolder":	"",
	"CurExec":	"Program",
	"AutoTaskFolder":	"",
	"ACServerFolder":	"C:\\ACROVIEW\\MultiAprog",
	"ReportFolder":	"",
	"ElectricInsertionCheck":	0,
	"strWorkOrder":	"001030012634",
	"strOperator":	"Admin",
	"MaxProduceValue":	0,
	"AutoTaskFileExt":	"tsk",
	"AutoTaskLoadCmd":	3,
	"WebServiceInterface":	"http://127.0.0.1:8080",
	"MESMode":	"Enable",
	"ProjectMode":	"ManualCreate",
	"AutoMode":	"Auto",
	"AutomaticType":	"IPS5000",
	"ReportURL":	"",
	"EnBarPrint":	0,
	"ScanComPort":	6,
	"ReInitIndex":	0,
	"StartIndex":	1,
	"SyslogEnable":	0,
	"TotalNum":	1,
	"ProgramIndex":	1,
	"ItemNum":	"12.012.0003.0006",
	"SoftVer":	"1.0.12.99",
	"Manufactor":	"AC",
	"IcNum":	"TC58CYG0S3HRAIG",
	"DeviceName":	"DEVICE001",
	"SoftMainVer":	"",
	"Account":	"BurmAdmin",
	"Pwd":	"950567374fc4216316f929cff74ba8bf",
	"UseCode":	"000004",
	"Serviceproviderid":	"1",
	"CheckDay":	7,
	"LocalServer":	0,
	"DoHttpTest":	0,
	"WorkStationID":	"1001",
	"EnPrint":	1,
	"PrintPort":	5000,
	"PrintIP":	"127.0.0.1"
}